Workbook

Sheet 3 Statement Model
A1: $ In millions
B2: Apple INC
B3: APPL
B4: 3 Statement Financial Summary
B8: Income Statement | C8: 2023 | D8: =C8+1 -> 2024 | E8: =D8+1 -> 2025 | F8: =E8+1 -> 2026 | G8: =F8+1 -> 2027 | H8: =G8+1 -> 2028 | I8: =H8+1 -> 2029 | J8: =I8+1 -> 2030
A9: x | B9: Net Sales (Revenue) | C9: 383285 | D9: 391035 | E9: 416161 | F9: =E9*(1+F28) -> 449453.88 | G9: =F9*(1+G28) -> 485410.19 | H9: =G9*(1+H28) -> 524243.01 | I9: =H9*(1+I28) -> 566182.45 | J9: =I9*(1+J28) -> 611477.04
B10: COGS | C10: -214137 | D10: -210352 | E10: -220960 | F10: =-F9*(1-F29) -> -240457.83 | G10: =-G9*(1-G29) -> -259694.45 | H10: =-H9*(1-H29) -> -280470.01 | I10: =-I9*(1-I29) -> -302907.61 | J10: =-J9*(1-J29) -> -327140.22
B11: Gross Profit | C11: =C9+C10 -> 169148 | D11: =D9+D10 -> 180683 | E11: =E9+E10 -> 195201 | F11: =F9+F10 -> 208996.05 | G11: =G9+G10 -> 225715.74 | H11: =H9+H10 -> 243773 | I11: =I9+I10 -> 263274.84 | J11: =J9+J10 -> 284336.82
B12: R&D | C12: -29915 | D12: -31370 | E12: -34550 | F12: =-F9*F30 -> -35956.31 | G12: =-G9*G30 -> -38832.815 | H12: =-H9*H30 -> -41939.44 | I12: =-I9*I30 -> -45294.596 | J12: =-J9*J30 -> -48918.163
B13: SG&A | C13: -24392 | D13: -26097 | E13: -27601 | F13: =-F9*F31 -> -29214.502 | G13: =-G9*G31 -> -31551.662 | H13: =-H9*H31 -> -34075.795 | I13: =-I9*I31 -> -36801.859 | J13: =-J9*J31 -> -39746.008
B14: Operating Income | C14: =C11+C12+C13 -> 114841 | D14: =D11+D12+D13 -> 123216 | E14: =E11+E12+E13 -> 133050 | F14: =F11+F12+F13 -> 143825.24 | G14: =G11+G12+G13 -> 155331.26 | H14: =H11+H12+H13 -> 167757.76 | I14: =I11+I12+I13 -> 181178.38 | J14: =J11+J12+J13 -> 195672.65
B15: Other Income/Expense, Net | C15: -565 | D15: 269 | E15: -321 | F15: 0 | G15: 0 | H15: 0 | I15: 0 | J15: 0
B16: Provision for Income Taxes | C16: -16741 | D16: -29749 | E16: -20719 | F16: =-F14*F32 -> -22292.912 | G16: =-G14*G32 -> -24076.345 | H16: =-H14*H32 -> -26002.453 | I16: =-I14*I32 -> -28082.649 | J16: =-J14*J32 -> -30329.261
B17: Net Income | C17: =C14+C15+C16 -> 97535 | D17: =D14+D15+D16 -> 93736 | E17: =E14+E15+E16 -> 112010 | F17: =F14+F15+F16 -> 121532.33 | G17: =G14+G15+G16 -> 131254.92 | H17: =H14+H15+H16 -> 141755.31 | I17: =I14+I15+I16 -> 153095.73 | J17: =J14+J15+J16 -> 165343.39
B19: Historical Drivers
B21: Revenue Growth % | D21: =D9/C9 -1 -> 0.020219941 | E21: =E9/D9 -1 -> 0.064255118
B22: Gross Margin % | C22: =(C11/C9) -> 0.4413113 | D22: =(D11/D9) -> 0.4620635 | E22: =(E11/E9) -> 0.46905164
B23: R&D as a % of Revenue | C23: =-(C12/C9) -> 0.078048971 | D23: =-(D12/D9) -> 0.080222998 | E23: =-(E12/E9) -> 0.083020754
B24: SG&A as a % of Revenue | C24: =-(C13/C9) -> 0.063639328 | D24: =-(D13/D9) -> 0.066738272 | E24: =-(E13/E9) -> 0.066322889
A26: x
B27: Growth Assumptions
B28: Revenue Growth % | F28: 0.08 | G28: 0.08 | H28: 0.08 | I28: 0.08 | J28: 0.08
B29: Gross Margin % | F29: 0.465 | G29: 0.465 | H29: 0.465 | I29: 0.465 | J29: 0.465
B30: R&D as a % of Revenue | F30: 0.08 | G30: 0.08 | H30: 0.08 | I30: 0.08 | J30: 0.08
B31: SG&A as a % of Revenue | F31: 0.065 | G31: 0.065 | H31: 0.065 | I31: 0.065 | J31: 0.065
B32: Tax Rate | F32: 0.155 | G32: 0.155 | H32: 0.155 | I32: 0.155 | J32: 0.155
B33: Days Sales Outstanding | F33: 30 | G33: 30 | H33: 30 | I33: 30 | J33: 30
B34: Days Inventory Outstanding | F34: 11 | G34: 11 | H34: 11 | I34: 11 | J34: 11
B35: Days Payable Outstanding | F35: 105 | G35: 105 | H35: 105 | I35: 105 | J35: 105
A36: x | B36: CAPEX | F36: 0.03 | G36: 0.03 | H36: 0.03 | I36: 0.03 | J36: 0.03
B37: Cash Dividends | F37: 15000 | G37: 15000 | H37: 15000 | I37: 15000 | J37: 15000
B38: Depreciation as a % | F38: 0.17 | G38: 0.17 | H38: 0.17 | I38: 0.17 | J38: 0.17
B39: Diluted Shares Outstanding | D39: 15408 | E39: 15005 | F39: =E39*(1-0.02) -> 14704.9 | G39: =F39*(1-0.02) -> 14410.802 | H39: =G39*(1-0.02) -> 14122.586 | I39: =H39*(1-0.02) -> 13840.134 | J39: =I39*(1-0.02) -> 13563.332
B42: Balance Sheet
B43: Cash and Equivalents | D43: 29943 | E43: 35934 | F43: =F112 -> 63200.536 | G43: =G112 -> 101342.05 | H43: =H112 -> 149869.42 | I43: =I112 -> 209588.93 | J43: =J112 -> 281375.53
B44: Marketable Securities | D44: 35228 | E44: 18763 | F44: 18763 | G44: 18763 | H44: 18763 | I44: 18763 | J44: 18763
B45: Accounts Receivable | D45: 33410 | E45: 39777 | F45: =(F33/365)*F9 -> 36941.415 | G45: =(G33/365)*G9 -> 39896.728 | H45: =(H33/365)*H9 -> 43088.466 | I45: =(I33/365)*I9 -> 46535.544 | J45: =(J33/365)*J9 -> 50258.387
B46: Vendor Non-trade Receivables | D46: 32833 | E46: 33180 | F46: 33180 | G46: 33180 | H46: 33180 | I46: 33180 | J46: 33180
B47: Inventories | D47: 7286 | E47: 5718 | F47: =(F34/365)*-F10 -> 7246.6742 | G47: =(G34/365)*-G10 -> 7826.4081 | H47: =(H34/365)*-H10 -> 8452.5208 | I47: =(I34/365)*-I10 -> 9128.7225 | J47: =(J34/365)*-J10 -> 9859.0202
B48: Other Current Assets | D48: 14287 | E48: 14585 | F48: 14585 | G48: 14585 | H48: 14585 | I48: 14585 | J48: 14585
B49: Total Current Assets | D49: =SUM(D43:D48) -> 152987 | E49: =SUM(E43:E48) -> 147957 | F49: =SUM(F43:F48) -> 173916.63 | G49: =SUM(G43:G48) -> 215593.18 | H49: =SUM(H43:H48) -> 267938.41 | I49: =SUM(I43:I48) -> 331781.19 | J49: =SUM(J43:J48) -> 408020.94
B50: Marketable Securities | D50: 91479 | E50: 77723 | F50: 77723 | G50: 77723 | H50: 77723 | I50: 77723 | J50: 77723
B51: PP&E | D51: 45680 | E51: 49834 | F51: =E51-F95-F79 -> 54845.836 | G51: =F51-G95-G79 -> 60084.35 | H51: =G51-H95-H79 -> 65597.301 | I51: =H51-I95-I79 -> 71431.233 | J51: =I51-J95-J79 -> 77632.235
B52: Other Non-current assets | D52: 74834 | E52: 83727 | F52: 83727 | G52: 83727 | H52: 83727 | I52: 83727 | J52: 83727
B53: Total Non-current assets | D53: =SUM(D50:D52) -> 211993 | E53: =SUM(E50:E52) -> 211284 | F53: =SUM(F50:F52) -> 216295.84 | G53: =SUM(G50:G52) -> 221534.35 | H53: =SUM(H50:H52) -> 227047.3 | I53: =SUM(I50:I52) -> 232881.23 | J53: =SUM(J50:J52) -> 239082.23
B54: Total Assets | D54: =D49+D53 -> 364980 | E54: =E49+E53 -> 359241 | F54: =F49+F53 -> 390212.46 | G54: =G49+G53 -> 437127.53 | H54: =H49+H53 -> 494985.71 | I54: =I49+I53 -> 564662.43 | J54: =J49+J53 -> 647103.18
B56: Accounts Payable | D56: 68960 | E56: 69860 | F56: =(F35/365)*-F10 -> 69172.799 | G56: =(G35/365)*-G10 -> 74706.623 | H56: =(H35/365)*-H10 -> 80683.153 | I56: =(I35/365)*-I10 -> 87137.805 | J56: =(J35/365)*-J10 -> 94108.83
B57: Other Current Liabilities | D57: 78304 | E57: 66387 | F57: 66387 | G57: 66387 | H57: 66387 | I57: 66387 | J57: 66387
B58: Deferred Revenue | D58: 8249 | E58: 9055 | F58: 9055 | G58: 9055 | H58: 9055 | I58: 9055 | J58: 9055
B59: Commercial Paper | D59: 9967 | E59: 7979 | F59: 7979 | G59: 7979 | H59: 7979 | I59: 7979 | J59: 7979
B60: Term Debt | D60: 10912 | E60: 12350 | F60: 12350 | G60: 12350 | H60: 12350 | I60: 12350 | J60: 12350
B61: Total Current Liabilities | D61: =SUM(D56:D60) -> 176392 | E61: =SUM(E56:E60) -> 165631 | F61: =SUM(F56:F60) -> 164943.8 | G61: =SUM(G56:G60) -> 170477.62 | H61: =SUM(H56:H60) -> 176454.15 | I61: =SUM(I56:I60) -> 182908.81 | J61: =SUM(J56:J60) -> 189879.83
B62: Term Debt | D62: 85750 | E62: 78328 | F62: 78328 | G62: 78328 | H62: 78328 | I62: 78328 | J62: 78328
B63: Other Non-current Liabilities | D63: 45888 | E63: 41549 | F63: 41549 | G63: 41549 | H63: 41549 | I63: 41549 | J63: 41549
B64: Total Non-Current liabilities | D64: =SUM(D62:D63) -> 131638 | E64: =SUM(E62:E63) -> 119877 | F64: =SUM(F62:F63) -> 119877 | G64: =SUM(G62:G63) -> 119877 | H64: =SUM(H62:H63) -> 119877 | I64: =SUM(I62:I63) -> 119877 | J64: =SUM(J62:J63) -> 119877
B65: Total Liabilities | D65: =D64+D61 -> 308030 | E65: =E64+E61 -> 285508 | F65: =F64+F61 -> 284820.8 | G65: =G64+G61 -> 290354.62 | H65: =H64+H61 -> 296331.15 | I65: =I64+I61 -> 302785.81 | J65: =J64+J61 -> 309756.83
B67: Common Stock and APIC | D67: 83276 | E67: 93568 | F67: =E67+F80 -> 106431 | G67: =F67+G80 -> 119294 | H67: =G67+H80 -> 132157 | I67: =H67+I80 -> 145020 | J67: =I67+J80 -> 157883
B68: Accumulated deficit | D68: -19154 | E68: -14264 | F68: =(E68+F17)-F37+F103 -> 4531.6625 | G68: =(F68+G17)-G37+G103 -> 33049.911 | H68: =(G68+H17)-H37+H103 -> 72068.553 | I68: =(H68+I17)-I37+I103 -> 122427.62 | J68: =(I68+J17)-J37+J103 -> 185034.35
B69: Accumulated other loss | D69: -7172 | E69: -5571 | F69: -5571 | G69: -5571 | H69: -5571 | I69: -5571 | J69: -5571
B70: Total Shareholders Equity | D70: =SUM(D67:D69) -> 56950 | E70: =SUM(E67:E69) -> 73733 | F70: =SUM(F67:F69) -> 105391.66 | G70: =SUM(G67:G69) -> 146772.91 | H70: =SUM(H67:H69) -> 198654.55 | I70: =SUM(I67:I69) -> 261876.62 | J70: =SUM(J67:J69) -> 337346.35
A72: x | B72: Balance? | D72: =IF(ROUND(D70+D65-D54,2)=0,"Balanced","Error") -> Balanced | E72: =IF(ROUND(E70+E65-E54,2)=0,"Balanced","Error") -> Balanced | F72: =IF(ROUND(F70+F65-F54,2)=0,"Balanced","Error") -> Balanced | G72: =IF(ROUND(G70+G65-G54,2)=0,"Balanced","Error") -> Balanced | H72: =IF(ROUND(H70+H65-H54,2)=0,"Balanced","Error") -> Balanced | I72: =IF(ROUND(I70+I65-I54,2)=0,"Balanced","Error") -> Balanced | J72: =IF(ROUND(J70+J65-J54,2)=0,"Balanced","Error") -> Balanced
B74: Statement of Cash Flows
B76: Operating Activities
B78: Net income | C78: 96995 | D78: 93736 | E78: 112010 | F78: =F17 -> 121532.33 | G78: =G17 -> 131254.92 | H78: =H17 -> 141755.31 | I78: =I17 -> 153095.73 | J78: =J17 -> 165343.39
B79: D&A | C79: 11519 | D79: 11445 | E79: 11698 | F79: =F38*E51 -> 8471.78 | G79: =G38*F51 -> 9323.7922 | H79: =H38*G51 -> 10214.339 | I79: =I38*H51 -> 11151.541 | J79: =J38*I51 -> 12143.31
B80: Share-based Compensation | C80: 10833 | D80: 11688 | E80: 12863 | F80: =E80 -> 12863 | G80: =F80 -> 12863 | H80: =G80 -> 12863 | I80: =H80 -> 12863 | J80: =I80 -> 12863
B81: Other | C81: -2227 | D81: -2266 | E81: -89 | F81: 0 | G81: 0 | H81: 0 | I81: 0 | J81: 0
B82: Accounts Receivable, net | C82: -1688 | D82: -3788 | E82: -6682 | F82: =E45-F45 -> 2835.5852 | G82: =F45-G45 -> -2955.3132 | H82: =G45-H45 -> -3191.7382 | I82: =H45-I45 -> -3447.0773 | J82: =I45-J45 -> -3722.8435
B83: Vendor non-trade receivable | C83: 1271 | D83: -1356 | E83: -347 | F83: =E46-F46 -> 0 | G83: =F46-G46 -> 0 | H83: =G46-H46 -> 0 | I83: =H46-I46 -> 0 | J83: =I46-J46 -> 0
B84: Inventories | C84: -1618 | D84: -1046 | E84: 1400 | F84: =E47-F47 -> -1528.6742 | G84: =F47-G47 -> -579.73394 | H84: =G47-H47 -> -626.11265 | I84: =H47-I47 -> -676.20166 | J84: =I47-J47 -> -730.2978
B85: Other current and non-current assets | C85: -5684 | D85: -11731 | E85: -9197 | F85: 0 | G85: 0 | H85: 0 | I85: 0 | J85: 0
B86: Accounts Payable | C86: -1889 | D86: 6020 | E86: 902 | F86: =F56-E56 -> -687.2008 | G86: =G56-F56 -> 5533.8239 | H86: =H56-G56 -> 5976.5299 | I86: =I56-H56 -> 6454.6522 | J86: =J56-I56 -> 6971.0244
B87: Other Current and non-current liabilities | C87: 3031 | D87: 15552 | E87: -11076 | F87: 0 | G87: 0 | H87: 0 | I87: 0 | J87: 0
B88: Cash Generated by operating activities | C88: =SUM(C78:C87) -> 110543 | D88: =SUM(D78:D87) -> 118254 | E88: =SUM(E78:E87) -> 111482 | F88: =SUM(F78:F87) -> 143486.82 | G88: =SUM(G78:G87) -> 155440.48 | H88: =SUM(H78:H87) -> 166991.33 | I88: =SUM(I78:I87) -> 179441.65 | J88: =SUM(J78:J87) -> 192867.58
B91: Investing Activities
B92: Purchases or Marketable Securities | C92: -29513 | D92: -48656 | E92: -24407 | F92: 0 | G92: 0 | H92: 0 | I92: 0 | J92: 0
B93: Proceeds from maturities of marketable securities | C93: 39686 | D93: 51211 | E93: 40907 | F93: 0 | G93: 0 | H93: 0 | I93: 0 | J93: 0
B94: Proceeds from sales of marketable securities | C94: 5828 | D94: 11135 | E94: 12890 | F94: 0 | G94: 0 | H94: 0 | I94: 0 | J94: 0
B95: Payments for acq. Of PP&E | C95: -10959 | D95: -9447 | E95: -12715 | F95: =-F36*F9 -> -13483.616 | G95: =-G36*G9 -> -14562.306 | H95: =-H36*H9 -> -15727.29 | I95: =-I36*I9 -> -16985.473 | J95: =-J36*J9 -> -18344.311
B96: Other | C96: -1337 | D96: -1308 | E96: -1480 | F96: 0 | G96: 0 | H96: 0 | I96: 0 | J96: 0
B97: Cash Generated by investing activities | C97: =SUM(C92:C96) -> 3705 | D97: =SUM(D92:D96) -> 2935 | E97: =SUM(E92:E96) -> 15195 | F97: =SUM(F92:F96) -> -13483.616 | G97: =SUM(G92:G96) -> -14562.306 | H97: =SUM(H92:H96) -> -15727.29 | I97: =SUM(I92:I96) -> -16985.473 | J97: =SUM(J92:J96) -> -18344.311
B99: Finance Activities
B101: Payments for taxes related to net settlement of equity | C101: -5431 | D101: -5441 | E101: -5960 | F101: 0 | G101: 0 | H101: 0 | I101: 0 | J101: 0
B102: Payments for dividends | C102: -15025 | D102: -15234 | E102: -15421 | F102: =-F37 -> -15000 | G102: =-G37 -> -15000 | H102: =-H37 -> -15000 | I102: =-I37 -> -15000 | J102: =-J37 -> -15000
B103: Repurchases of common stock | C103: -77550 | D103: -94949 | E103: -90711 | F103: -87736.667 | G103: -87736.667 | H103: -87736.667 | I103: -87736.667 | J103: -87736.667
B104: Proceeds from issuance of term debt | C104: 5228 | D104: 0 | E104: 4481 | F104: 0 | G104: 0 | H104: 0 | I104: 0 | J104: 0
B105: Repayments of term debt | C105: -11151 | D105: -9958 | E105: -10932 | F105: 0 | G105: 0 | H105: 0 | I105: 0 | J105: 0
B106: Proceeds from commercial paper | C106: -3978 | D106: 3960 | E106: -2032 | F106: 0 | G106: 0 | H106: 0 | I106: 0 | J106: 0
B107: Other | C107: -581 | D107: -361 | E107: -111 | F107: 0 | G107: 0 | H107: 0 | I107: 0 | J107: 0
B108: Cash used in financing activities | C108: =SUM(C101:C107) -> -108488 | D108: =SUM(D101:D107) -> -121983 | E108: =SUM(E101:E107) -> -120686 | F108: =SUM(F101:F107) -> -102736.67 | G108: =SUM(G101:G107) -> -102736.67 | H108: =SUM(H101:H107) -> -102736.67 | I108: =SUM(I101:I107) -> -102736.67 | J108: =SUM(J101:J107) -> -102736.67
B110: Net Change in Cash | C110: =C88+C97+C108 -> 5760 | D110: =D88+D97+D108 -> -794 | E110: =E88+E97+E108 -> 5991 | F110: =F88+F97+F108 -> 27266.536 | G110: =G88+G97+G108 -> 38141.512 | H110: =H88+H97+H108 -> 48527.37 | I110: =I88+I97+I108 -> 59719.508 | J110: =J88+J97+J108 -> 71786.607
B111: Beginning Cash | E111: =D43 -> 29943 | F111: =E43 -> 35934 | G111: =F43 -> 63200.536 | H111: =G43 -> 101342.05 | I111: =H43 -> 149869.42 | J111: =I43 -> 209588.93
B112: Ending Cash | E112: =SUM(E110:E111) -> 35934 | F112: =SUM(F110:F111) -> 63200.536 | G112: =SUM(G110:G111) -> 101342.05 | H112: =SUM(H110:H111) -> 149869.42 | I112: =SUM(I110:I111) -> 209588.93 | J112: =SUM(J110:J111) -> 281375.53

Sheet DCF Valuation
A2: x | B2: Apple DCF
B3: AAPL
B4: DCF Valuation | C4: Ticker: | D4: AAPL | F4: Implied Share Price | H4: =G33 -> 134.70156
B5: $ in millions | C5: Date: | D5: 46269 | F5: Today's Share price | H5: =WACC!C7 -> 319.97
B7: Assumptions
B8: % of OPEX | C8: 0.12 | D8: 0.12 | E8: 0.12 | F8: 0.12 | G8: 0.12
B9: WACC | C9: =WACC!$C$24 -> 0.10101505
B10: Terminal Growth Rate | C10: 0.035
C13: 1 | D13: 2 | E13: 3 | F13: 4 | G13: 5
B14: DCF | C14: 2026 | D14: =C14+1 -> 2027 | E14: =D14+1 -> 2028 | F14: =E14+1 -> 2029 | G14: =F14+1 -> 2030
B15: Revenue | C15: ='3 Statement Model'!F9 -> 449453.88 | D15: ='3 Statement Model'!G9 -> 485410.19 | E15: ='3 Statement Model'!H9 -> 524243.01 | F15: ='3 Statement Model'!I9 -> 566182.45 | G15: ='3 Statement Model'!J9 -> 611477.04
B16: EBIT | C16: ='3 Statement Model'!F14 -> 143825.24 | D16: ='3 Statement Model'!G14 -> 155331.26 | E16: ='3 Statement Model'!H14 -> 167757.76 | F16: ='3 Statement Model'!I14 -> 181178.38 | G16: ='3 Statement Model'!J14 -> 195672.65
B17: Taxes | C17: =-C16*'3 Statement Model'!F32 -> -22292.912 | D17: =-D16*'3 Statement Model'!G32 -> -24076.345 | E17: =-E16*'3 Statement Model'!H32 -> -26002.453 | F17: =-F16*'3 Statement Model'!I32 -> -28082.649 | G17: =-G16*'3 Statement Model'!J32 -> -30329.261
B18: NOPAT | C18: =C16+C17 -> 121532.33 | D18: =D16+D17 -> 131254.92 | E18: =E16+E17 -> 141755.31 | F18: =F16+F17 -> 153095.73 | G18: =G16+G17 -> 165343.39
B19: D&A | C19: ='3 Statement Model'!F79 -> 8471.78 | D19: ='3 Statement Model'!G79 -> 9323.7922 | E19: ='3 Statement Model'!H79 -> 10214.339 | F19: ='3 Statement Model'!I79 -> 11151.541 | G19: ='3 Statement Model'!J79 -> 12143.31
B20: CAPEX | C20: ='DCF Valuation'!C15*'3 Statement Model'!F36 -> 13483.616 | D20: ='DCF Valuation'!D15*'3 Statement Model'!G36 -> 14562.306 | E20: ='DCF Valuation'!E15*'3 Statement Model'!H36 -> 15727.29 | F20: ='DCF Valuation'!F15*'3 Statement Model'!I36 -> 16985.473 | G20: ='DCF Valuation'!G15*'3 Statement Model'!J36 -> 18344.311
B21: Change in NWC | C21: =('3 Statement Model'!F45+'3 Statement Model'!F47+'3 Statement Model'!F48-'3 Statement Model'!F56-'3 Statement Model'!F57)-('3 Statement Model'!E45+'3 Statement Model'!E47+'3 Statement Model'!E48-'3 Statement Model'!E56-'3 Statement Model'!E57) -> -619.71021 | D21: =('3 Statement Model'!G45+'3 Statement Model'!G47+'3 Statement Model'!G48-'3 Statement Model'!G56-'3 Statement Model'!G57)-('3 Statement Model'!F45+'3 Statement Model'!F47+'3 Statement Model'!F48-'3 Statement Model'!F56-'3 Statement Model'!F57) -> -1998.7768 | E21: =('3 Statement Model'!H45+'3 Statement Model'!H47+'3 Statement Model'!H48-'3 Statement Model'!H56-'3 Statement Model'!H57)-('3 Statement Model'!G45+'3 Statement Model'!G47+'3 Statement Model'!G48-'3 Statement Model'!G56-'3 Statement Model'!G57) -> -2158.679 | F21: =('3 Statement Model'!I45+'3 Statement Model'!I47+'3 Statement Model'!I48-'3 Statement Model'!I56-'3 Statement Model'!I57)-('3 Statement Model'!H45+'3 Statement Model'!H47+'3 Statement Model'!H48-'3 Statement Model'!H56-'3 Statement Model'!H57) -> -2331.3733 | G21: =('3 Statement Model'!J45+'3 Statement Model'!J47+'3 Statement Model'!J48-'3 Statement Model'!J56-'3 Statement Model'!J57)-('3 Statement Model'!I45+'3 Statement Model'!I47+'3 Statement Model'!I48-'3 Statement Model'!I56-'3 Statement Model'!I57) -> -2517.8831
B22: UFCF | C22: =C18+C19-C20-C21 -> 117140.2 | D22: =D18+D19-D20-D21 -> 128015.18 | E22: =E18+E19-E20-E21 -> 138401.04 | F22: =F18+F19-F20-F21 -> 149593.17 | G22: =G18+G19-G20-G21 -> 161660.27
B23: Present Value of FCF | C23: =C22/(1+$C$9)^C13 -> 106392.92 | D23: =D22/(1+$C$9)^D13 -> 105602.68 | E23: =E22/(1+$C$9)^E13 -> 103695.42 | F23: =F22/(1+$C$9)^F13 -> 101797.88 | G23: =G22/(1+$C$9)^G13 -> 99916.458
B26: Terminal Value | G26: =(G22*(1+C10))/(C9-C10) -> 2534549
A27: x | B27: Present Value of Terminal Value | G27: =G26/(1+C9)^G13 -> 1566514.5
B28: Enterprise Value | G28: =SUM(C23:G23,G27) -> 2083919.8
B29: Cash | G29: ='3 Statement Model'!E112 -> 35934
B30: Debt | G30: ='3 Statement Model'!E59+'3 Statement Model'!E60+'3 Statement Model'!E62 -> 98657
B31: Equity Value | G31: =G28+G29-G30 -> 2021196.8
B32: Shares | G32: ='3 Statement Model'!E39 -> 15005
B33: Share Price | G33: =G31/G32 -> 134.70156
B39: Sensitivity Table
B40: =G33 -> 134.70156 | C40: 0.08 | D40: 0.09 | E40: 0.095 | F40: 0.101 | G40: 0.11 | H40: 0.12
B41: 0.02 | C41: 156.9966 | D41: 133.38218 | E41: 123.94382 | F41: 114.16172 | G41: 101.9445 | H41: 90.961675
B42: 0.025 | C42: 168.99514 | D42: 141.76944 | E42: 131.08092 | F42: 120.11682 | G42: 106.58307 | H42: 94.565317
B43: 0.03 | C43: 183.39338 | D43: 151.55457 | E43: 139.31603 | F43: 126.91068 | G43: 111.80146 | H43: 98.569364
B44: 0.035 | C44: 200.99124 | D44: 163.11882 | E44: 148.92365 | F44: 134.7339 | G44: 117.71563 | H44: 103.04447
B45: 0.04 | C45: 222.98856 | D45: 176.99592 | E45: 160.27813 | F45: 143.83962 | G45: 124.47469 | H45: 108.07897

Sheet WACC
B2: WACC
A4: x | B4: WACC
B5: WACC = (% of Equity * Cost of Equity)+ (% of Debt * Cost of Debt*(1 - tax rate))
B6: Cost of Equity = Risk Free Rate * beta( expected return - Risk Free Rate)
B7: Current Apple stock (9/4/26) | C7: 319.97
B9: Debt | C9: ='3 Statement Model'!D59+'3 Statement Model'!D60+'3 Statement Model'!D62 -> 106629
B10: % Debt | C10: =C9/C22 -> 0.022160102
B11: Cost of Debt | C11: 0.042
B12: Tax Rate | C12: ='3 Statement Model'!F32 -> 0.155
B15: Equity Value | C15: =C7*'3 Statement Model'!F39 -> 4705126.9
B16: % Equity | C16: =C15/C22 -> 0.9778399
B17: Cost of Equity | C17: =C18+(C19*C20) -> 0.1025
B18: Risk Free Rate | C18: 0.048
B19: Beta | C19: 1.09
B20: Market Risk Premium | C20: 0.05
B22: Debt + Equity | C22: =C15+C9 -> 4811755.9
A24: x | B24: WACC | C24: =(C16*C17)+(C10*C11*(1-C12)) -> 0.10101505
